cap/__init__.py
cap/bus.py
cap/client.py
cap/runtime.py
cap/worker.py
cap/pb/__init__.py
cap/pb/cordum/__init__.py
cap/pb/cordum/agent/__init__.py
cap/pb/cordum/agent/v1/__init__.py
cap/pb/cordum/agent/v1/alert_pb2.py
cap/pb/cordum/agent/v1/alert_pb2_grpc.py
cap/pb/cordum/agent/v1/buspacket_pb2.py
cap/pb/cordum/agent/v1/buspacket_pb2_grpc.py
cap/pb/cordum/agent/v1/heartbeat_pb2.py
cap/pb/cordum/agent/v1/heartbeat_pb2_grpc.py
cap/pb/cordum/agent/v1/job_pb2.py
cap/pb/cordum/agent/v1/job_pb2_grpc.py
cap/pb/cordum/agent/v1/safety_pb2.py
cap/pb/cordum/agent/v1/safety_pb2_grpc.py
tests/test_conformance.py
tests/test_runtime.py
tests/test_sdk.py
cap_sdk_python-2.0.19.dist-info/METADATA
cap_sdk_python-2.0.19.dist-info/WHEEL
cap_sdk_python-2.0.19.dist-info/top_level.txt
cap_sdk_python-2.0.19.dist-info/RECORD
