Metadata-Version: 2.4
Name: cap-sdk-python
Version: 2.0.19
Summary: CAP (Cordum Agent Protocol) Python SDK
Project-URL: Homepage, https://github.com/cordum-io/cap
Requires-Python: >=3.9
Requires-Dist: protobuf>=4.25.0
Requires-Dist: grpcio>=1.59.0
Requires-Dist: nats-py>=2.6.0
Requires-Dist: cryptography>=41.0.0
Requires-Dist: pydantic>=2.6.0
Requires-Dist: redis>=5.0.0
